setup.py
hearthistory/__init__.py
hearthistory/cli.py
hearthistory.egg-info/PKG-INFO
hearthistory.egg-info/SOURCES.txt
hearthistory.egg-info/dependency_links.txt
hearthistory.egg-info/entry_points.txt
hearthistory.egg-info/requires.txt
hearthistory.egg-info/top_level.txt